datamax/__init__.py
pydatamax-0.2.0.dist-info/licenses/LICENSE
pydatamax-0.2.0.dist-info/METADATA
pydatamax-0.2.0.dist-info/WHEEL
pydatamax-0.2.0.dist-info/entry_points.txt
pydatamax-0.2.0.dist-info/top_level.txt
pydatamax-0.2.0.dist-info/RECORD
